thatway/__init__.py
thatway/base.py
thatway-0.6.0.dist-info/LICENSE
thatway-0.6.0.dist-info/METADATA
thatway-0.6.0.dist-info/WHEEL
thatway-0.6.0.dist-info/top_level.txt
thatway-0.6.0.dist-info/RECORD
